labelle/__init__.py
labelle/_version.py
labelle/metadata.py
labelle/_vendor/matplotlib.pyi
labelle/_vendor/matplotlib/LICENSE
labelle/_vendor/matplotlib/LICENSE_AMSFONTS
labelle/_vendor/matplotlib/LICENSE_BAKOMA
labelle/_vendor/matplotlib/LICENSE_CARLOGO
labelle/_vendor/matplotlib/LICENSE_COLORBREWER
labelle/_vendor/matplotlib/LICENSE_COURIERTEN
labelle/_vendor/matplotlib/LICENSE_DEJAVU
labelle/_vendor/matplotlib/LICENSE_JSXTOOLS_RESIZE_OBSERVER
labelle/_vendor/matplotlib/LICENSE_QHULL
labelle/_vendor/matplotlib/LICENSE_QT4_EDITOR
labelle/_vendor/matplotlib/LICENSE_SOLARIZED
labelle/_vendor/matplotlib/LICENSE_STIX
labelle/_vendor/matplotlib/LICENSE_YORICK
labelle/_vendor/matplotlib/font_manager.py
labelle/cli/cli.py
labelle/gui/common.py
labelle/gui/gui.py
labelle/gui/q_actions.py
labelle/gui/q_device_selector.py
labelle/gui/q_label_widgets.py
labelle/gui/q_labels_list.py
labelle/gui/q_render.py
labelle/gui/q_settings_toolbar.py
labelle/gui/tests/test_gui.py
labelle/lib/barcode_to_image.py
labelle/lib/barcode_writer.py
labelle/lib/config_file.py
labelle/lib/constants.py
labelle/lib/env_config.py
labelle/lib/font_config.py
labelle/lib/logger.py
labelle/lib/outputs.py
labelle/lib/unicode_blocks.py
labelle/lib/utils.py
labelle/lib/devices/__init__.py
labelle/lib/devices/device_manager.py
labelle/lib/devices/dymo_labeler.py
labelle/lib/devices/online_device_manager.py
labelle/lib/devices/usb_device.py
labelle/lib/render_engines/__init__.py
labelle/lib/render_engines/barcode.py
labelle/lib/render_engines/barcode_with_text.py
labelle/lib/render_engines/empty.py
labelle/lib/render_engines/exceptions.py
labelle/lib/render_engines/horizontally_combined.py
labelle/lib/render_engines/margins.py
labelle/lib/render_engines/picture.py
labelle/lib/render_engines/print_payload.py
labelle/lib/render_engines/print_preview.py
labelle/lib/render_engines/qr.py
labelle/lib/render_engines/render_context.py
labelle/lib/render_engines/render_engine.py
labelle-1.4.2.dist-info/METADATA
labelle-1.4.2.dist-info/WHEEL
labelle-1.4.2.dist-info/entry_points.txt
labelle-1.4.2.dist-info/licenses/LICENSE
labelle-1.4.2.dist-info/RECORD
