Metadata-Version: 2.4
Name: labelle
Version: 1.4.2
Summary: Open-source label printing software
Project-URL: Homepage, https://github.com/labelle-org/labelle
Project-URL: source, https://github.com/labelle-org/labelle
Project-URL: tracker, https://github.com/labelle-org/labelle/issues
Author-email: "Sebastian J. Bronner" <waschtl@sbronner.com>
Maintainer-email: Tomer Shalev <tshalev@proofpoint.com>, Ben Mares <services-labelle@tensorial.com>, Tomek Szczęsny <mctom@tlen.pl>
License-Expression: Apache-2.0
License-File: LICENSE
Classifier: License :: OSI Approved :: Apache Software License
Classifier: Operating System :: POSIX :: Linux
Classifier: Programming Language :: Python :: 3.8
Classifier: Programming Language :: Python :: 3.9
Classifier: Programming Language :: Python :: 3.10
Classifier: Programming Language :: Python :: 3.11
Classifier: Programming Language :: Python :: 3.12
Classifier: Topic :: Printing
Requires-Python: <4,>=3.8
Requires-Dist: darkdetect
Requires-Dist: pillow<11,>=8.1.2
Requires-Dist: platformdirs
Requires-Dist: pyqrcode<2,>=1.2.1
Requires-Dist: pyqt6
Requires-Dist: python-barcode<0.16,>=0.13.1
Requires-Dist: pyusb
Requires-Dist: typer>=0.16.0
Provides-Extra: test
Requires-Dist: pytest-cov; extra == 'test'
Requires-Dist: pytest-image-diff; extra == 'test'
Requires-Dist: pytest-qt; extra == 'test'
Requires-Dist: pytest-xvfb; extra == 'test'
